contract_analyzer/__init__.py
contract_analyzer/chunk.py
contract_analyzer/chunking_system.py
contract_analyzer/contract_analysis_rag.py
contract_analyzer-0.2.0.dist-info/METADATA
contract_analyzer-0.2.0.dist-info/WHEEL
contract_analyzer-0.2.0.dist-info/top_level.txt
contract_analyzer-0.2.0.dist-info/RECORD
