Metadata-Version: 2.1
Name: contract-analyzer
Version: 0.2.0
Summary: A RAG system for contract analysis
Home-page: https://github.com/ahmetkumass/contract-analyzer.git
Author: Ahmet Kumas
Author-email: ahmetkumas@outlook.com
Classifier: Development Status :: 4 - Beta
Classifier: Intended Audience :: Developers
Classifier: License :: OSI Approved :: MIT License
Classifier: Operating System :: POSIX :: Linux
Classifier: Programming Language :: Python :: 3
Classifier: Programming Language :: Python :: 3.7
Classifier: Programming Language :: Python :: 3.8
Classifier: Programming Language :: Python :: 3.9
Requires-Python: >=3.7
Requires-Dist: numpy
Requires-Dist: scikit-learn
Requires-Dist: sentence-transformers
Requires-Dist: transformers
Requires-Dist: torch
Requires-Dist: pdfplumber
Requires-Dist: PyPDF2
Requires-Dist: accelerate
